trueloss.py
trueloss-0.1.2.dist-info/LICENSE
trueloss-0.1.2.dist-info/METADATA
trueloss-0.1.2.dist-info/WHEEL
trueloss-0.1.2.dist-info/top_level.txt
trueloss-0.1.2.dist-info/RECORD
