Metadata-Version: 2.1
Name: trueloss
Version: 0.1.2
Summary: A library for computing true training loss in Keras models without regularization effects.
Home-page: https://github.com/trueloss/trueloss
Author: Siddique Abusaleh
Author-email: trueloss.py@gmail.com
Classifier: Programming Language :: Python :: 3
Classifier: Programming Language :: Python :: 3.9
Classifier: Programming Language :: Python :: 3.10
Classifier: Programming Language :: Python :: 3.11
Classifier: License :: OSI Approved :: MIT License
Classifier: Operating System :: OS Independent
Classifier: Development Status :: 3 - Alpha
Classifier: Intended Audience :: Developers
Classifier: Intended Audience :: Education
Classifier: Intended Audience :: Science/Research
Classifier: Topic :: Scientific/Engineering :: Artificial Intelligence
Classifier: Topic :: Software Development :: Libraries :: Python Modules
Classifier: Environment :: Console
Classifier: Natural Language :: English
Requires-Python: >=3.9
License-File: LICENSE
